{
	"$schema": "../../node_modules/turbo/schema.json",
	"extends": ["//"],
	"tasks": {
		"typegen:local": {
			"inputs": ["alchemy.run.ts", "package.json", "tsconfig.json"],
			"outputs": []
		},
		"typegen:prod": {
			"inputs": ["alchemy.run.ts", "package.json", "tsconfig.json"],
			"outputs": []
		},
		"typecheck:local": {
			"dependsOn": ["typegen:local"],
			"inputs": [
				"alchemy.run.ts",
				"package.json",
				"tsconfig.json",
				"$TURBO_ROOT$/tsconfig.base.json"
			],
			"outputs": []
		},
		"typecheck:prod": {
			"dependsOn": ["typegen:prod"],
			"inputs": [
				"alchemy.run.ts",
				"package.json",
				"tsconfig.json",
				"$TURBO_ROOT$/tsconfig.base.json"
			],
			"outputs": []
		},
		"deploy:prod": {
			"dependsOn": ["typecheck:prod"],
			"cache": false,
			"inputs": ["alchemy.run.ts", "package.json"],
			"outputs": []
		},
		"deploy:staging": {
			"dependsOn": ["typecheck:prod"],
			"cache": false,
			"inputs": ["alchemy.run.ts", "package.json"],
			"outputs": []
		},
		"deploy:preview": {
			"dependsOn": ["typecheck:prod"],
			"cache": false,
			"inputs": ["alchemy.run.ts", "package.json"],
			"outputs": []
		},
		"destroy:prod": {
			"cache": false,
			"outputs": []
		},
		"destroy:staging": {
			"cache": false,
			"outputs": []
		},
		"destroy:preview": {
			"cache": false,
			"outputs": []
		}
	}
}
